[
    {
        "id":"reboot",
        "hidden":true,
        "type":"button",
        "content":[
            {
                "label":"REBOOT",
                "command":"D0|REBOOT;D1|REBOOT",
                "type":"sync",
                "expected_value":"RESTARTED|D0;RESTARTED|D1"
            }
        ]
    },
    {
        "id":"laser",
        "label":"Laser State",
        "description":"Change the laser state",
        "type":"switches_group",
        "content":[
            {
                "label":"OFF",
                "command":"D0|LASER|OFF",
                "type":"sync",
                "expected_value":"UPDATED|LASER",
                "default":true
            },
            {
                "label":"Red",
                "command":"D0|LASER|RED",
                "type":"sync",
                "expected_value":"UPDATED|LASER"
            },
            {
                "label":"Green",
                "command":"D0|LASER|GREEN",
                "type":"sync",
                "expected_value":"UPDATED|LASER"
            }
        ]
    },
    {
        "id":"gain",
        "label":"Gain",
        "description":"Change the gain",
        "type":"switches_group",
        "content":[
            {
                "label":"VERY_LOW",
                "command":"D0|GAIN|VERY_LOW",
                "type":"sync",
                "expected_value":"UPDATED|GAIN",
                "default":true
            },
            {
                "label":"LOW",
                "command":"D0|GAIN|LOW",
                "type":"sync",
                "expected_value":"UPDATED|GAIN"
            },
            {
                "label":"HIGH",
                "command":"D0|GAIN|HIGH",
                "type":"sync",
                "expected_value":"UPDATED|GAIN"
            },
            {
                "label":"VERY_HIGH",
                "command":"D0|GAIN|VERY_HIGH",
                "type":"sync",
                "expected_value":"UPDATED|GAIN"
            }
        ]
    },
    {
        "id":"slit",
        "label":"Slit Position",
        "description":"Change the slit position",
        "type":"buttons_group",
        "content":[
            {
                "label":"LEFT",
                "command":"D0|SLIT|LEFT",
                "type":"async"
            },
            {
                "label":"LEFT",
                "command":"D0|SLIT|RIGHT",
                "type":"async"
            }
        ]
    },
    {
        "id":"distance",
        "label":"Distance D",
        "description":"Change the distance D",
        "type":"buttons_group",
        "content":[
            {
                "label":"INCREASE",
                "command":"D1|DISTANCE|INCREASE",
                "type":"sync",
                "expected_value":"xx",
                "action":"displayCurrentDistance"
            },
            {
                "label":"DECREASE",
                "command":"D1|DISTANCE|DECREASE",
                "type":"sync",
                "expected_value":"xx",
                "action":"displayCurrentDistance"
            }
        ]
    },
    {
        "id":"measure",
        "description":"Measure the pattern",
        "type":"button",
        "content":[
            {
                "label":"MEASURE",
                "command":"D1|MEASURE|START",
                "type":"sync",
                "expected_value":"[[x1,y1],[x2,y2]...]",
                "action":"getChart"
            }
        ]
    }
]